di2008_python/__init__.py
di2008_python/di2008_layout_settings.py
di2008_python/di2008_python.py
di2008_python-1.4.0.dist-info/licenses/LICENSE
di2008_python-1.4.0.dist-info/METADATA
di2008_python-1.4.0.dist-info/WHEEL
di2008_python-1.4.0.dist-info/top_level.txt
di2008_python-1.4.0.dist-info/RECORD
