Metadata-Version: 2.4
Name: di2008-python
Version: 1.4.0
Summary: Python Interface for the DATAQ DI-2008 DAQ
Author-email: Clark Hensley <ch3136@msstate.edu>
Maintainer-email: Clark Hensley <ch3136@msstate.edu>
License: MIT License
Project-URL: Source, https://github.com/Computational-Mechanics-Materials-Lab/DI2008_Python
Requires-Python: >=3.10
License-File: LICENSE
Requires-Dist: pyserial>=3.5
Requires-Dist: tomli; python_version < "3.11"
Dynamic: license-file
